python_plugins/__about__.py
python_plugins/__init__.py
python_plugins/crypto/__init__.py
python_plugins/crypto/aes_cipher.py
python_plugins/crypto/mixbyte.py
python_plugins/crypto/pbkdf_fernet.py
python_plugins/crypto/simple_fernet.py
python_plugins/crypto/tarmix.py
python_plugins/crypto/txtfile_cipher.py
python_plugins/crypto/zip7mix.py
python_plugins/email/__init__.py
python_plugins/email/smtp.py
python_plugins/examples/datetime.py
python_plugins/examples/hashes.py
python_plugins/examples/higher_order_functions.py
python_plugins/examples/postgresql_dump.py
python_plugins/examples/pretty.py
python_plugins/examples/random_string.py
python_plugins/examples/run_jwt.py
python_plugins/examples/run_process.py
python_plugins/examples/xml2dict.py
python_plugins/examples/tkinter/calculate.py
python_plugins/models/__init__.py
python_plugins/models/update.py
python_plugins/models/mixins/__init__.py
python_plugins/models/mixins/data_mixin.py
python_plugins/models/mixins/primary_key_mixin.py
python_plugins/models/mixins/timestamp_mixin.py
python_plugins/models/mixins/token_minxin.py
python_plugins/models/mixins/user_minxin.py
python_plugins/ospath/__init__.py
python_plugins/ospath/walk_remove.py
python_plugins-1.0.2.dist-info/METADATA
python_plugins-1.0.2.dist-info/WHEEL
python_plugins-1.0.2.dist-info/licenses/LICENSE.rst
python_plugins-1.0.2.dist-info/RECORD
