Metadata-Version: 2.4
Name: python-plugins
Version: 1.0.2
Summary: A collection of Python functions and classes.
Project-URL: Documentation, https://python-plugins.readthedocs.io
Project-URL: Source, https://github.com/ojso/python-plugins
Project-URL: Homepage, https://github.com/ojso/python-plugins
Author-email: David Hua <david.dong.hua@gmail.com>
License: MIT License
License-File: LICENSE.rst
Keywords: plugin,utils
Classifier: Development Status :: 3 - Alpha
Classifier: Intended Audience :: Developers
Classifier: License :: OSI Approved :: MIT License
Classifier: Programming Language :: Python
Classifier: Programming Language :: Python :: 3
Classifier: Programming Language :: Python :: 3.10
Classifier: Programming Language :: Python :: 3.11
Classifier: Topic :: Software Development :: Build Tools
Requires-Python: >=3.10
Requires-Dist: cryptography>=44.0
Provides-Extra: jwt
Requires-Dist: pyjwt; extra == 'jwt'
Provides-Extra: pillow
Requires-Dist: pillow; extra == 'pillow'
Provides-Extra: qrcode
Requires-Dist: qrcode; extra == 'qrcode'
Provides-Extra: requests
Requires-Dist: requests; extra == 'requests'
Provides-Extra: sqlalchemy
Requires-Dist: sqlalchemy; extra == 'sqlalchemy'
